pcbdl/__init__.py
pcbdl/allegro.py
pcbdl/base.py
pcbdl/context.py
pcbdl/defined_at.py
pcbdl/html.py
pcbdl/netlistsvg.py
pcbdl/small_parts.py
pcbdl-0.1.1.dist-info/LICENSE
pcbdl-0.1.1.dist-info/METADATA
pcbdl-0.1.1.dist-info/WHEEL
pcbdl-0.1.1.dist-info/top_level.txt
pcbdl-0.1.1.dist-info/RECORD
