Metadata-Version: 2.1
Name: pcbdl
Version: 0.1.1
Summary: A programming way to design schematics.
Home-page: https://github.com/google/pcbdl
Author: Google LLC
License: Apache-2.0
Keywords: eda,hdl,electronics,netlist,hardware,schematics
Platform: UNKNOWN
Classifier: Intended Audience :: Developers
Classifier: License :: OSI Approved :: Apache Software License
Classifier: Operating System :: OS Independent
Classifier: Programming Language :: Python :: 3
Classifier: Topic :: Scientific/Engineering :: Electronic Design Automation (EDA)
Classifier: Topic :: System :: Hardware
Requires-Dist: pygments
